README.md
setup.py
qbase/__init__.py
qbase/example.py
qbase/common/__init__.py
qbase/common/check_pro_los.py
qbase/common/configer.py
qbase/common/dbsql.py
qbase/common/emailUtil.py
qbase/common/get_data.py
qbase/common/loger.py
qbase/common/mmaper.py
qbase/common/mySql.py
qbase/common/until.py
qbase/dao/__init__.py
qbase/dao/accountMapper.py
qbase/dao/okexResultMapper.py
qbase/dao/positionMapper.py
qbase/entity/__init__.py
qbase/entity/signal.py
qbase/enum/__init__.py
qbase/enum/enum.py
qbase/okex/__init__.py
qbase/okex/account_api.py
qbase/okex/client.py
qbase/okex/consts.py
qbase/okex/ett_api.py
qbase/okex/exceptions.py
qbase/okex/futures_api.py
qbase/okex/httpMD5Util.py
qbase/okex/lever_api.py
qbase/okex/okcoinFutureAPI.py
qbase/okex/okcoinSpotAPI.py
qbase/okex/okexData.py
qbase/okex/spot_api.py
qbase/okex/utils.py
qbase/okex/websockets.py
qbase/threading/__init__.py
qbase/threading/accountMain.py
qbase/threading/transaction.py
qbase/transaction/__init__.py
qbase/transaction/transactions.py
qbase_beequants.egg-info/PKG-INFO
qbase_beequants.egg-info/SOURCES.txt
qbase_beequants.egg-info/dependency_links.txt
qbase_beequants.egg-info/requires.txt
qbase_beequants.egg-info/top_level.txt